[
    {
        "id": "liquid-glass",
        "image": "https://res.cloudinary.com/barthkosi/video/upload/liquid-glass-demo.mp4",
        "title": "Liquid glass shader",
        "description": "Recreated liquid glass in the browser with shaders.",
        "link": "/explorations/glass"
    },
    {
        "id": "vinyl-player",
        "image": "https://res.cloudinary.com/barthkosi/image/upload/vinyl-player-cover.webp",
        "title": "Vinyl player",
        "description": "A fully functioning vinyl player built in framer.",
        "link": "/explorations/vinyl"
    }
]